{"html_attributions":[],"result":{"address_components":[{"long_name":"251","short_name":"251","types":["street_number"]},{"long_name":"Main Street","short_name":"Main St","types":["route"]},{"long_name":"Charlestown","short_name":"Charlestown","types":["neighborhood","political"]},{"long_name":"Boston","short_name":"Boston","types":["locality","political"]},{"long_name":"Suffolk County","short_name":"Suffolk County","types":["administrative_area_level_2","political"]},{"long_name":"Massachusetts","short_name":"MA","types":["administrative_area_level_1","political"]},{"long_name":"United States","short_name":"US","types":["country","political"]},{"long_name":"02129","short_name":"02129","types":["postal_code"]}],"adr_address":"<span class=\"street-address\">251 Main St</span>, <span class=\"locality\">Boston</span>, <span class=\"region\">MA</span> <span class=\"postal-code\">02129</span>, <span class=\"country-name\">USA</span>","business_status":"OPERATIONAL","current_opening_hours":{"open_now":true,"periods":[{"close":{"date":"2023-02-20","day":1,"time":"0100"},"open":{"date":"2023-02-19","day":0,"time":"0900"}},{"close":{"date":"2023-02-21","day":2,"time":"0100"},"open":{"date":"2023-02-20","day":1,"time":"1130"}},{"close":{"date":"2023-02-21","day":2,"time":"2359","truncated":true},"open":{"date":"2023-02-21","day":2,"time":"1130"}},{"close":{"date":"2023-02-15","day":3,"time":"0100"},"open":{"date":"2023-02-15","day":3,"time":"0000","truncated":true}},{"close":{"date":"2023-02-16","day":4,"time":"0100"},"open":{"date":"2023-02-15","day":3,"time":"1130"}},{"close":{"date":"2023-02-17","day":5,"time":"0100"},"open":{"date":"2023-02-16","day":4,"time":"1130"}},{"close":{"date":"2023-02-18","day":6,"time":"0100"},"open":{"date":"2023-02-17","day":5,"time":"1130"}},{"close":{"date":"2023-02-19","day":0,"time":"0100"},"open":{"date":"2023-02-18","day":6,"time":"0900"}}],"weekday_text":["Monday: 11:30 AM – 1:00 AM","Tuesday: 11:30 AM – 1:00 AM","Wednesday: 11:30 AM – 1:00 AM","Thursday: 11:30 AM – 1:00 AM","Friday: 11:30 AM – 1:00 AM","Saturday: 9:00 AM – 1:00 AM","Sunday: 9:00 AM – 1:00 AM"]},"delivery":true,"dine_in":true,"editorial_summary":{"language":"en","overview":"Wood-fired pizzas & more gastropub grub in a comfortable setting of brick & weathered woods."},"formatted_address":"251 Main St, Boston, MA 02129, USA","formatted_phone_number":"(617) 337-5191","geometry":{"location":{"lat":42.3768973,"lng":-71.0660355},"viewport":{"northeast":{"lat":42.3781942802915,"lng":-71.06474281970848},"southwest":{"lat":42.3754963197085,"lng":-71.06744078029149}}},"icon":"https://maps.gstatic.com/mapfiles/place_api/icons/v1/png_71/restaurant-71.png","icon_background_color":"#FF9E67","icon_mask_base_uri":"https://maps.gstatic.com/mapfiles/place_api/icons/v2/restaurant_pinlet","international_phone_number":"+1 617-337-5191","name":"Monument Charlestown Restaurant & Tavern","opening_hours":{"open_now":true,"periods":[{"close":{"day":1,"time":"0100"},"open":{"day":0,"time":"0900"}},{"close":{"day":2,"time":"0100"},"open":{"day":1,"time":"1130"}},{"close":{"day":3,"time":"0100"},"open":{"day":2,"time":"1130"}},{"close":{"day":4,"time":"0100"},"open":{"day":3,"time":"1130"}},{"close":{"day":5,"time":"0100"},"open":{"day":4,"time":"1130"}},{"close":{"day":6,"time":"0100"},"open":{"day":5,"time":"1130"}},{"close":{"day":0,"time":"0100"},"open":{"day":6,"time":"0900"}}],"weekday_text":["Monday: 11:30 AM – 1:00 AM","Tuesday: 11:30 AM – 1:00 AM","Wednesday: 11:30 AM – 1:00 AM","Thursday: 11:30 AM – 1:00 AM","Friday: 11:30 AM – 1:00 AM","Saturday: 9:00 AM – 1:00 AM","Sunday: 9:00 AM – 1:00 AM"]},"photos":[{"height":1200,"html_attributions":["<a href=\"https://maps.google.com/maps/contrib/101160430263147138813\">Monument Charlestown Restaurant &amp; Tavern</a>"],"photo_reference":"AfLeUgPR-9rdbaqG01_TlGoLMFeHM17fc2UaI43XW92klWErUw6_n9z9nUhmKVcY-8EIwoHTX5ncAqZbVbQACZdtSdZnuyNraVsoJReJ2w6BxY9XwcTQUxEwQXkQ0mU70F2q7y-0-uYmmKTz0VisSHFk-Aave2X5I8QBVojUea-T-dxlQVD-","width":1800},{"height":3024,"html_attributions":["<a href=\"https://maps.google.com/maps/contrib/104985266122614520342\">George</a>"],"photo_reference":"AfLeUgNOtsHJQg-Ck3EjZHz1qlhvXxu6sidh-EjJjnefk-5HuYoj7a89vP7uGYrN7LJuNtGk43UIdPnokJ2G-kBpd2VKt9caOLir8LA84MB7m4pgw1MVQQHM2enwX9ebY-RI0N9ZTOT8JyiMK6SdNTr1Hne2w5U1_jsxTuzKMOE1o6GF8qPe","width":4032},{"height":4032,"html_attributions":["<a href=\"https://maps.google.com/maps/contrib/112874787137044467907\">S PJ</a>"],"photo_reference":"AfLeUgMxkDQUsZqMyRTNibXulC1R3tqtK2MX-A3Gd4vPYrr0iyuj3m_fZsaIfUTPtmPFyCiEdT2mXpZQ-SUe_-_V_6EHsmEZIepTCF7VloxsUN0rm2asrOmsXRQKoZI_FEEFuRNbr8CZoL7cjOa1XlBqSWdZeAnBe6OTKgUrx9dM4Z5FgxAY","width":3024},{"height":4032,"html_attributions":["<a href=\"https://maps.google.com/maps/contrib/104985266122614520342\">George</a>"],"photo_reference":"AfLeUgNaXKFef0uWRpHjSgAs1ELRmh9HSfp5R4qZS5jX_w4frzNRGW1eV_4yHnSlXLt7HChj9b78ftHRV80g6E_fE9iAnTj4y3sSrKK0hVM3X18I_-gcdmMxz4G3sqo5_x_opeNbgbSh56ff89IwVCAaB3ln8U9tZSGqqo7v0h6j3sonU8L4","width":3024},{"height":4032,"html_attributions":["<a href=\"https://maps.google.com/maps/contrib/104189375534708078486\">ChenWei Lin (阿暈)</a>"],"photo_reference":"AfLeUgOCcszbyXm_gzXdbm0yFVazz1B36Z3Fecr2mYUmo23y-oMF-J5SkVEG0oO6ZRagRIoYavxLHT3nHRhDKcTfnNgaZrH8vRe697zxLakXwTGoZQ3dxBdDEQm4cDZpgv3NMKfAaqeT_WLcC6YvGjtlqeyXoEHaRi8I5WxmYeuXgCWOxXW2","width":3024},{"height":3104,"html_attributions":["<a href=\"https://maps.google.com/maps/contrib/113931453671709509076\">Olivier Bradley</a>"],"photo_reference":"AfLeUgMEFvJ2DGyljm4XzoXrsgQB2YcBewyxTxHs7qV6xiqjCnhejjwj4xfQzEjfbSAIat0fwaosmpn9cFkZZ0LKOtifLBFiAId9G8Rx9zBB0YWkxlVVsjVUVuCtFlt40-meik2eG2sDZosKiMiWM9nhwz0EL7JNY811OT0vdXFBC82_dhTU","width":3024},{"height":3072,"html_attributions":["<a href=\"https://maps.google.com/maps/contrib/116379907226450015493\">A ML</a>"],"photo_reference":"AfLeUgNthBtqEqaEA428QbUsZiHI6Rp9pdB-G0Il1nZPIcyH5yxKXn67Z1w-yDxdRpFWpheG_ks34hB-jCSOfqKx84FPqtrSvyxZGve8btuZvlBEeVZTgQABuaLatnzNGpGOMb3x7GSop-brHLjKL_TQKdPsowyhcr3a12d1jjKcx4vYJe9v","width":4080},{"height":9248,"html_attributions":["<a href=\"https://maps.google.com/maps/contrib/113262663842080384297\">Cathy Clark</a>"],"photo_reference":"AfLeUgO19K1ns7vNbSSRbpwRAXp8TWrXQ2ItHXzyUfRd_rz_444mTel1W5Y__rfwgDSMzC-fVRBCxrqXOvxXXtcz_i5MOc37AlFfQIGiCeixefTSQDgk7fu8R36MYZXT_FaYkVb96_Jl2SS1Z5CxgKRuFVyFfP7pw0yFxQfH1pWVsDeOdxyf","width":6936},{"height":2268,"html_attributions":["<a href=\"https://maps.google.com/maps/contrib/114422743972419935706\">Ritesh Mukherjee</a>"],"photo_reference":"AfLeUgNLFf3mAySk8ve4JwbbJnfU0H8uNtPJq2kQhK-XgFsaZZbgU_oG4UE1JmwNH17RDRbS1uOzwon-sZsQGNt2kkNJMGYd5uL8ZV1er8d1YS6Ax_ZFjj4pHO8zB0IkGc7IAV-sbwnsTAOKoqZxw7uUuexZBk_nUo6G4n3D1b79EgIkq9E","width":4032},{"height":4032,"html_attributions":["<a href=\"https://maps.google.com/maps/contrib/110308768051626494140\">Marina Reginaldo</a>"],"photo_reference":"AfLeUgM3SPWjz2DnCtg1Dg8T6fsiXR45wOgkq-2u3F9oJ27IEChP-qSvFVOO1TpeSC1QYVbSyFYDsy5uv1b04_GmCSSSpe02dmQ9TbKPl3r7-hgNeQeJkZeI5g-UTD73LqVDl6oewSeN6w-LCAViW7Ljou21JNKfxrj2GqfJcQe-GvuhiQ9b","width":3024}],"place_id":"ChIJR0jyIuxw44kRaaA2TCmdnmk","plus_code":{"compound_code":"9WGM+QH Boston, MA, USA","global_code":"87JC9WGM+QH"},"price_level":2,"rating":4.6,"reference":"ChIJR0jyIuxw44kRaaA2TCmdnmk","reservable":true,"reviews":[{"author_name":"Marina Reginaldo","author_url":"https://www.google.com/maps/contrib/110308768051626494140/reviews","language":"en","original_language":"en","profile_photo_url":"https://lh3.googleusercontent.com/a-/AD5-WCn8EifuptvuG-4G0ZqJnceoKz_3WnpVbBifXLu3hYs=s128-c0x00000000-cc-rp-mo-ba4","rating":5,"relative_time_description":"4 months ago","text":"The best pancakes I’ve ever had in my life.\nWe went for brunch, the place was very busy but we got seated as soon as we got there. The restaurant itself is beautiful, the waitresses were very very nice, which made the experience even better.\nNow, the food: the pancakes are insanely delicious, we went there during Easter and they had the special pancakes made with cadbury chocolate 🥹 SO WORTHY!\nThe experience was so wonderful and the food was so good that I’m definitely coming back!!","time":1664851094,"translated":false},{"author_name":"Cathy Clark","author_url":"https://www.google.com/maps/contrib/113262663842080384297/reviews","language":"en","original_language":"en","profile_photo_url":"https://lh3.googleusercontent.com/a/AEdFTp7G6-znjrv53nBGONCxR_ZZ_aXckqUjLAq-hV3R=s128-c0x00000000-cc-rp-mo-ba4","rating":5,"relative_time_description":"5 months ago","text":"Great atmosphere with high tin ceiling, wooden booths and tables, red brick walls and outdoor seating on sidewalk tables with umbrellas, followed the locals here. Good food,  lunch and dinner menu, daily specials and friendly service. Pizza smelled great, went back for takeout salad this weekend, easy to find on Warren Street near Bunker Hill Monument. Worth a visit!","time":1663382835,"translated":false},{"author_name":"nathan nowicki","author_url":"https://www.google.com/maps/contrib/113173157611267941419/reviews","language":"en","original_language":"en","profile_photo_url":"https://lh3.googleusercontent.com/a-/AD5-WCljFS81jSQnYJvz6xuS3tcCH3F2fj5zMnfw2lSI=s128-c0x00000000-cc-rp-mo-ba5","rating":3,"relative_time_description":"10 months ago","text":"Arrived for diner. Almost walked out because of too long of a wait after being seated. Waiter arrived just as we were getting up. He was very attentive after that. The beer was really good. Ordered artichoke dip and it was lukewarm. It is served in a cold small skillet that I was able to hold in my hand. The waiter too it back and the kitchen made another that was perfect. I also ordered the carnitas tacos. They also came out lukewarm. My friend had the chicken sandwich, which he said was very good and hot. It came with a large amount of smash potatoes on the side. They also serve small rolls with a ricotta cheese spread that was very delicious. The main dishes took about an hour to be served. I didn't say anything about the tacos because by that time we were about ready to go. The waiter removed the dip from my bill, which was very nice and not expected. Perhaps a second chance next time I'm in town.","time":1649724340,"translated":false},{"author_name":"George","author_url":"https://www.google.com/maps/contrib/104985266122614520342/reviews","language":"en","original_language":"en","profile_photo_url":"https://lh3.googleusercontent.com/a-/AD5-WCluKLGpgf0eagNysgnn7o5YUZBmZUNO-7ELZmTXSi4=s128-c0x00000000-cc-rp-mo-ba5","rating":5,"relative_time_description":"2 weeks ago","text":"Awesome place. Consistently amazing food, either dine in or delivery, and the bar is long with tons of beers on tap. High quality ingredients and their pizza and wings and spectacular.","time":1674937580,"translated":false},{"author_name":"Erica Jaros","author_url":"https://www.google.com/maps/contrib/107227741341064162675/reviews","language":"en","original_language":"en","profile_photo_url":"https://lh3.googleusercontent.com/a-/AD5-WCmnjHub0DETZbRnP4Dkz1gLvn1dk_C17c78FjPd=s128-c0x00000000-cc-rp-mo","rating":5,"relative_time_description":"7 months ago","text":"The breakfast tacos and cinnamon toast brunch were amazing. The fancy fizz is pretty good if you want something fruity, but not sweet. The staff was great and the service was excellent.","time":1656256128,"translated":false}],"secondary_opening_hours":[{"open_now":false,"periods":[{"close":{"date":"2023-02-19","day":0,"time":"1500"},"open":{"date":"2023-02-19","day":0,"time":"0900"}},{"close":{"date":"2023-02-18","day":6,"time":"1500"},"open":{"date":"2023-02-18","day":6,"time":"0900"}}],"type":"BRUNCH","weekday_text":["Monday: Closed","Tuesday: Closed","Wednesday: Closed","Thursday: Closed","Friday: Closed","Saturday: 9:00 AM – 3:00 PM","Sunday: 9:00 AM – 3:00 PM"]}],"serves_beer":true,"serves_breakfast":true,"serves_brunch":true,"serves_dinner":true,"serves_lunch":true,"serves_vegetarian_food":true,"serves_wine":true,"takeout":true,"types":["restaurant","bar","food","point_of_interest","establishment"],"url":"https://maps.google.com/?cid=7610693221000585321","user_ratings_total":828,"utc_offset":-300,"vicinity":"251 Main Street, Boston","website":"https://www.monumentcharlestown.com/","wheelchair_accessible_entrance":true},"status":"OK"}