{"html_attributions":[],"result":{"address_components":[{"long_name":"659","short_name":"659","types":["street_number"]},{"long_name":"Boylston Street","short_name":"Boylston St","types":["route"]},{"long_name":"Back Bay","short_name":"Back Bay","types":["neighborhood","political"]},{"long_name":"Boston","short_name":"Boston","types":["locality","political"]},{"long_name":"Suffolk County","short_name":"Suffolk County","types":["administrative_area_level_2","political"]},{"long_name":"Massachusetts","short_name":"MA","types":["administrative_area_level_1","political"]},{"long_name":"United States","short_name":"US","types":["country","political"]},{"long_name":"02116","short_name":"02116","types":["postal_code"]}],"adr_address":"<span class=\"street-address\">659 Boylston St</span>, <span class=\"locality\">Boston</span>, <span class=\"region\">MA</span> <span class=\"postal-code\">02116</span>, <span class=\"country-name\">USA</span>","business_status":"OPERATIONAL","curbside_pickup":false,"current_opening_hours":{"open_now":false,"periods":[{"close":{"date":"2023-02-19","day":0,"time":"2200"},"open":{"date":"2023-02-19","day":0,"time":"1030"}},{"close":{"date":"2023-02-20","day":1,"time":"2200"},"open":{"date":"2023-02-20","day":1,"time":"1030"}},{"close":{"date":"2023-02-21","day":2,"time":"2200"},"open":{"date":"2023-02-21","day":2,"time":"1030"}},{"close":{"date":"2023-02-15","day":3,"time":"2200"},"open":{"date":"2023-02-15","day":3,"time":"1030"}},{"close":{"date":"2023-02-16","day":4,"time":"2200"},"open":{"date":"2023-02-16","day":4,"time":"1030"}},{"close":{"date":"2023-02-17","day":5,"time":"2200"},"open":{"date":"2023-02-17","day":5,"time":"1030"}},{"close":{"date":"2023-02-18","day":6,"time":"2200"},"open":{"date":"2023-02-18","day":6,"time":"1030"}}],"weekday_text":["Monday: 10:30 AM – 10:00 PM","Tuesday: 10:30 AM – 10:00 PM","Wednesday: 10:30 AM – 10:00 PM","Thursday: 10:30 AM – 10:00 PM","Friday: 10:30 AM – 10:00 PM","Saturday: 10:30 AM – 10:00 PM","Sunday: 10:30 AM – 10:00 PM"]},"delivery":true,"dine_in":true,"editorial_summary":{"language":"en","overview":"Locavore-friendly counter-serve chain specializing in organic salads & bowls."},"formatted_address":"659 Boylston St, Boston, MA 02116, USA","formatted_phone_number":"(617) 936-3464","geometry":{"location":{"lat":42.3500287,"lng":-71.078665},"viewport":{"northeast":{"lat":42.3512421302915,"lng":-71.0772662697085},"southwest":{"lat":42.3485441697085,"lng":-71.07996423029151}}},"icon":"https://maps.gstatic.com/mapfiles/place_api/icons/v1/png_71/restaurant-71.png","icon_background_color":"#FF9E67","icon_mask_base_uri":"https://maps.gstatic.com/mapfiles/place_api/icons/v2/restaurant_pinlet","international_phone_number":"+1 617-936-3464","name":"sweetgreen","opening_hours":{"open_now":false,"periods":[{"close":{"day":0,"time":"2200"},"open":{"day":0,"time":"1030"}},{"close":{"day":1,"time":"2200"},"open":{"day":1,"time":"1030"}},{"close":{"day":2,"time":"2200"},"open":{"day":2,"time":"1030"}},{"close":{"day":3,"time":"2200"},"open":{"day":3,"time":"1030"}},{"close":{"day":4,"time":"2200"},"open":{"day":4,"time":"1030"}},{"close":{"day":5,"time":"2200"},"open":{"day":5,"time":"1030"}},{"close":{"day":6,"time":"2200"},"open":{"day":6,"time":"1030"}}],"weekday_text":["Monday: 10:30 AM – 10:00 PM","Tuesday: 10:30 AM – 10:00 PM","Wednesday: 10:30 AM – 10:00 PM","Thursday: 10:30 AM – 10:00 PM","Friday: 10:30 AM – 10:00 PM","Saturday: 10:30 AM – 10:00 PM","Sunday: 10:30 AM – 10:00 PM"]},"photos":[{"height":1344,"html_attributions":["<a href=\"https://maps.google.com/maps/contrib/112700198785763793939\">sweetgreen</a>"],"photo_reference":"AfLeUgN2zuv0oGgb_Ztyz2Drc4mORpWCaT06UShZky07F_Mx6lL-EU8HdxUVI2mJuzFK-qftxtSBi-N-By7bRCIJuclbLVUcLYAtE2iNjFUwUF1qRO_Nw7iAkObb0f7Hmx9FjhtI3CMTYgXOg7HNZyho8y9zU9piMNpexceFtuR_zSMPeskp","width":2016},{"height":1080,"html_attributions":["<a href=\"https://maps.google.com/maps/contrib/112700198785763793939\">sweetgreen</a>"],"photo_reference":"AfLeUgNJuBnncUOh-jFAt891DdIpCJXZ_Yxh8e0mi5RngbzBvQ2feEL9XSUzk4dfqtxu11bovqQ5Y5hAOu3fgsGapfhSijG63bNGC__67VuHqf8MymqE2JWrYgtRvoeR3vTLuu8V1ewQMO74KwgL82lHnjomu4YszgTettGC47FBHUrmO_tk","width":1920},{"height":4000,"html_attributions":["<a href=\"https://maps.google.com/maps/contrib/112700198785763793939\">sweetgreen</a>"],"photo_reference":"AfLeUgN2bZ6AS5K8-th2kAuIyx-tRpXAs7O8HJe_SFJ0ksbv9TaFMWACjmLdeQrId-p1U3hTB08D9SmYFgjDSNDKazlrFSesjjtTxUUeVATHlAl-MzMBWlG95bng1OrSU8dMVXSJlPBO6fGNbiAmKstsGblljTZy1hvPRCrcBZ3gBha33DzA","width":3001},{"height":3000,"html_attributions":["<a href=\"https://maps.google.com/maps/contrib/112700198785763793939\">sweetgreen</a>"],"photo_reference":"AfLeUgP5_8g6OCvcze2YtjoxDLxhgJG4sQZadfuj-Ri0jds4dV1pbmz6xJZU4gET_ynW1ekFlh9lmqnWojcsCRLHlAm8jD_wLxVSCgTJ36YTz-q5ewsprz567BahSgyIx8RMs7q-313wFeEunnzdKR8bQfWwGXv418ynQApcBBNINid77xJ0","width":4001},{"height":4000,"html_attributions":["<a href=\"https://maps.google.com/maps/contrib/107558865385642826704\">Tony Evora</a>"],"photo_reference":"AfLeUgOvQQ_2mCmMgpF4jwdYvulLGidua0WcvMT0bvTa_7FDwrEZlOTHSSxsUyW6VJmiaF14dq3oOk8xHlxSEuj0hr2ZXodPhb7d1V2YCDeJnzsMnYqPT6ErKONsZNsAXNLYiVQ8WOomV7Iff4hwDtL4rq8lSfrOko_SVSTGtRiR0LiXjb39","width":1800},{"height":3001,"html_attributions":["<a href=\"https://maps.google.com/maps/contrib/112700198785763793939\">sweetgreen</a>"],"photo_reference":"AfLeUgP2c1WGJZ5s6Y1qkVAImJlB9fhvvPloCZ7XbRtxT1iiHPcT_TQ2jy4UrObSIh6MdrFjozEY7MbAdht37oNccLI45Wdzp8hvfR1XdFjYsnq5833Zyf01bDxRNcWxvOXpDn9jpW9jfG8plC-9Xj9PrnunnIsZMN3N_YAR7XE7bbr6bid_","width":4001},{"height":3024,"html_attributions":["<a href=\"https://maps.google.com/maps/contrib/114491395927030210513\">Jon Langbert</a>"],"photo_reference":"AfLeUgNaEh1_qDCRS8ME8s_Ssac-Q-TwjJ8oXxCnlHDSgqqUfJJ6t1PNgwPh63seLTComKcxwvpS0a3hqMYHSoBdQrFNMYcb4Uok_jlhrjokmgCc-FVlI73I9vF4jqVrB9CPa631eBJRMK72hqBoPIRzpGpw0XC6lLFLNE0zAzl2dBiO46jt","width":4032},{"height":1200,"html_attributions":["<a href=\"https://maps.google.com/maps/contrib/112700198785763793939\">sweetgreen</a>"],"photo_reference":"AfLeUgNCAgsbSvuYr0SOoa645qQk0OUnrDNADZIJqjLZajUb1TBjtoqh4k3iUVieFlDTiWxoeOQfuvvTEjGm6GVyGcLiYuHEsYsVzNIW7sKeO6N28qu969qgNPTDd57AeoQMVYo_ratFw9yz8DxSc4bhzC0-xZpzBDcjx_EvUB9pIdVlnN6o","width":1200},{"height":1280,"html_attributions":["<a href=\"https://maps.google.com/maps/contrib/112700198785763793939\">sweetgreen</a>"],"photo_reference":"AfLeUgO7I41QCUsUxri2SiNi4aaOxyOqrpVdHUwnHUUB2NF73msnS5hTe7jouKr5B9thndh20bzz6rQwqQWJH2MJ38_86Tjn89DiI6m5qMDH5jiIPirhPrVcI-tCi4Hef3nT664hqrFgE_a0y26vZyfnoPTNVJS_J6PheqM23rsdQxTl5gXw","width":1280},{"height":4032,"html_attributions":["<a href=\"https://maps.google.com/maps/contrib/101174106366481170465\">Dylan Prévost</a>"],"photo_reference":"AfLeUgOUGf4yNbcvXO2cDYpVVMuyJLewrMgKZCPiRKOkq4nHAAqG-5bdH4_nfFXd3J2fYf_5zgzqEP63yTMpwkTMCb1bOFa38H-wnqjIwkTngV8s7Ps6-j9KTiALkvoKAopJHKbczcl8gxEw62BVU0YwUxUBkHFPq8UKLXAGM2xVgMBVRGa-","width":3024}],"place_id":"ChIJa6jJFwx644kRCqw6ohQtC6c","plus_code":{"compound_code":"9W2C+2G Boston, MA, USA","global_code":"87JC9W2C+2G"},"price_level":2,"rating":4.4,"reference":"ChIJa6jJFwx644kRCqw6ohQtC6c","reservable":false,"reviews":[{"author_name":"Mona Jalal","author_url":"https://www.google.com/maps/contrib/100917947481290716905/reviews","language":"en","original_language":"en","profile_photo_url":"https://lh3.googleusercontent.com/a-/AD5-WCn41AOp8XGBkjVoUWTmotK5j9rrZpnriLMz8OOt_fs=s128-c0x00000000-cc-rp-mo-ba6","rating":5,"relative_time_description":"5 months ago","text":"Kale Caesar salad from this place is my favorite health food at around 450 calories. The staffs are very polite and friendly and there’s not much wait time. The only caveat is the store does not have a water machine. Addition of water to the store would be really great. I love sitting on the chair outside the store and do people watching at Copley Sq. The store is conveniently located right off Copley Square green line MBTA. The prices are reasonable. The portions are filling.\n\nUpdate: today I tried guacamole 🥑 greens with green goddess dressing and I really liked it. Highly recommend it.","time":1663467882,"translated":false},{"author_name":"Zane","author_url":"https://www.google.com/maps/contrib/102726370662604029144/reviews","language":"en","original_language":"en","profile_photo_url":"https://lh3.googleusercontent.com/a/AEdFTp6nL-DIWDQZp9ubBX0WxnxxLT66x3eZXSg8zGhL33I=s128-c0x00000000-cc-rp-mo-ba4","rating":2,"relative_time_description":"8 months ago","text":"Ordering to go is wildly painful. Instead of using the built in shelves with name labeling, the staff keeps the orders behind the register. This creates chaos as patrons must queue and ask for their to go orders individually, which the staff then finds slowly as they sort through the many orders behind them. I genuinely have no idea why they don't use the system built into the wall for this exact purpose.\n\nThe attached pictures are related. The first is the long line to pick up during the dinner rush, and the second is the unused wall system.\n\nAlso the salads are tasty but expensive.","time":1653575763,"translated":false},{"author_name":"Marcus Sanders","author_url":"https://www.google.com/maps/contrib/105219434628606290724/reviews","language":"en","original_language":"en","profile_photo_url":"https://lh3.googleusercontent.com/a-/AD5-WCm6eHJ7SgliMzeo4QzZYK8D2AYiO--hQeig_XbcNw=s128-c0x00000000-cc-rp-mo","rating":5,"relative_time_description":"a month ago","text":"It was my first time eating at a sweet greens and I must say that the food was fresh and the staff was exceptional. My server was Christian, he did a great job being patient while I built my own salad. I’d definitely recommend this location and will indeed return!","time":1671870458,"translated":false},{"author_name":"mark fumicello","author_url":"https://www.google.com/maps/contrib/107218364569118174143/reviews","language":"en","original_language":"en","profile_photo_url":"https://lh3.googleusercontent.com/a/AEdFTp6jA_G6etnn1CyM8D8vBwzWhUwH6ji74HFom76Y=s128-c0x00000000-cc-rp-mo","rating":1,"relative_time_description":"2 months ago","text":"I have to be one of this location’s most loyal customers, my office is on their block. Like over 1,000 salads. I just had my third salad in probably the past 6 mo that was either undressed or failed to include meat and they don’t respond to any feedback tickets which is just unacceptable for mistakes like that. I pay $12, leave, then find out I didn’t get what I paid for, then get no response from the company and eat a lackluster lunch. I feel this location is going downhill. Each time I pulled up the menu in the past month, they’re missing so many ingredients. So, no customer service whatsoever, lack of care in preparing orders, and a failure to keep a consistent menu. Not great","time":1669828848,"translated":false},{"author_name":"M Munford","author_url":"https://www.google.com/maps/contrib/103114460114297275112/reviews","language":"en","original_language":"en","profile_photo_url":"https://lh3.googleusercontent.com/a/AEdFTp7lJzNf5afy9D09qXQLLAhbUYy-G9mu_BErKivh=s128-c0x00000000-cc-rp-mo","rating":2,"relative_time_description":"3 months ago","text":"Gabrielle was super rude and unhelpful. They didn't have an ingredient for the salad I ordered. Asked if they had something similar and she simply replied \"no.\" Asked for Brussels sprouts in place of the missing item and she said \"no that doesn't come with the salad it's a premium item.\" But of course it's full price for a salad that's missing an ingredient god forbid you throw five brussel sprouts on the damn thing to make up for lacking all the original ingredients. Wouldn't have been so bad if she hadn't been rolling her eyes at me the whole time.","time":1667955104,"translated":false}],"serves_beer":false,"serves_dinner":true,"serves_lunch":true,"serves_vegetarian_food":true,"serves_wine":false,"takeout":true,"types":["meal_takeaway","restaurant","point_of_interest","food","establishment"],"url":"https://maps.google.com/?cid=12036763995722132490","user_ratings_total":619,"utc_offset":-300,"vicinity":"659 Boylston Street, Boston","website":"http://order.sweetgreen.com/?utm_source=google_listing&utm_medium=yext&utm_campaign=visit_main_website_CTA&y_source=1_MjYyMTY3NC03MTUtbG9jYXRpb24ud2Vic2l0ZQ%3D%3D","wheelchair_accessible_entrance":true},"status":"OK"}